{"8.729858665999998": "", "9.156865208": "out(V0,V1,V2):- in(V0,V1,V2),c3(V1),v8(V2),my_succ(V1,V3),in(V0,V3,V2).", "9.190151499999999": "out(V0,V1,V2):- in(V0,V1,V2),v2(V2),c1(V3),in(V0,V3,V2),lt(V3,V1).", "9.209587875": "out(V0,V1,V2):- in(V0,V1,V2),v8(V2),c1(V3),in(V0,V3,V2),lt(V3,V1).", "9.242148916000001": "out(V0,V1,V2):- in(V0,V1,V2),v8(V2),c2(V3),in(V0,V3,V2),lt(V3,V1).", "9.374112958000001": "out(V0,V1,V2):- in(V0,V1,V2),c3(V3),lt(V3,V1).", "9.383134083000002": "out(V0,V1,V2):- in(V0,V1,V2),c3(V3),in(V0,V3,V2),lt(V3,V1).", "9.497158082999999": "out(V0,V1,V2):- c2(V3),in(V0,V3,V2),lt(V3,V1).", "12.3484375": "out(V0,V1,V2):- c3(V3),in(V0,V3,V2),my_succ(V1,V4),lt(V3,V4).", "15.617316625": "out(V0,V1,V2):- c3(V3),in(V0,V3,V2),lt(V3,V1),empty(V0,V4),lt(V1,V4).", "371.26022008300004": "out(V0,V1,V2):- c5(V3),in(V0,V3,V2),lt(V3,V1),in(V0,V5,V4),lt(V1,V5).", "376.08481379100004": "out(V0,V1,V2):- c3(V3),in(V0,V3,V2),lt(V3,V1),in(V0,V5,V4),lt(V1,V5).", "1013.294691791": "out(V0,V1,V2):- in(V0,V1,V2),c5(V3),lt(V3,V1),in(V0,V5,V2),empty(V4,V5).\nout(V0,V1,V2):- c9(V3),in(V0,V3,V2),lt(V3,V1),my_succ(V1,V5),in(V0,V5,V4).\nout(V0,V1,V2):- in(V0,V1,V2),my_succ(V3,V1),v8(V4),in(V0,V5,V4),lt(V5,V3).\nout(V0,V1,V2):- c3(V4),in(V0,V4,V2),lt(V4,V1),add(V1,V4,V3),empty(V5,V3).\nout(V0,V1,V2):- c9(V3),my_succ(V3,V5),add(V4,V5,V1),in(V0,V4,V2),lt(V4,V5)."}